fings/FiNGS.py
fings/__init__.py
fings/filter_functions.py
fings/filter_parameters.txt
fings/icgc_filter_parameters.txt
fings/primary.py
fings/shared_functions.py
fings/exampledata/normal.bam
fings/exampledata/normal.bam.bai
fings/exampledata/s2.raw.vcf
fings/exampledata/test.sh
fings/exampledata/tumor.bam
fings/exampledata/tumor.bam.bai
fings-1.7.1.dist-info/LICENSE
fings-1.7.1.dist-info/METADATA
fings-1.7.1.dist-info/WHEEL
fings-1.7.1.dist-info/entry_points.txt
fings-1.7.1.dist-info/top_level.txt
fings-1.7.1.dist-info/RECORD
