Metadata-Version: 2.1
Name: fings
Version: 1.7.1
Summary: Filters for Next Generation Sequencing
Home-page: https://github.com/cpwardell/FiNGS
Author: Christopher Wardell
Author-email: github@cpwardell.com
License: UNKNOWN
Platform: UNKNOWN
Classifier: Programming Language :: Python :: 3
Classifier: License :: OSI Approved :: Apache Software License
Classifier: Operating System :: OS Independent
Requires-Python: >=3.6
Requires-Dist: pyvcf
Requires-Dist: pysam
Requires-Dist: numpy
Requires-Dist: scipy
Requires-Dist: pandas
Requires-Dist: joblib
Requires-Dist: seaborn
Requires-Dist: statsmodels
Requires-Dist: editdistance
